synlinkpy/__init__.py
synlinkpy-0.0.14.dist-info/LICENSE
synlinkpy-0.0.14.dist-info/METADATA
synlinkpy-0.0.14.dist-info/WHEEL
synlinkpy-0.0.14.dist-info/top_level.txt
synlinkpy-0.0.14.dist-info/RECORD
