Metadata-Version: 2.1
Name: synlinkpy
Version: 0.0.14
Summary: HTTP Python Wrapper for Synaccess SynLink PDU HTTP API.
Home-page: https://synaccess.com
Author: Kevin Han
Author-email: Kevin Han <kevin.han@synaccess.com>
Project-URL: Homepage, https://github.com/synaccess/synlink-py
Project-URL: Bug Tracker, https://github.com/synaccess/synlink-py/issues
Keywords: synlink,pdu,api,client
Classifier: Programming Language :: Python :: 3
Classifier: License :: OSI Approved :: MIT License
Classifier: Operating System :: OS Independent
Requires-Python: >=3.6
License-File: LICENSE
Requires-Dist: requests>=2.2.1
Requires-Dist: requests-toolbelt>=0.9.1
